exact_clustering-0.5.1.dist-info/METADATA
exact_clustering-0.5.1.dist-info/WHEEL
exact_clustering-0.5.1.dist-info/licenses/LICENSE-APACHE
exact_clustering-0.5.1.dist-info/licenses/LICENSE-MIT
exact_clustering/__init__.py
exact_clustering/__init__.pyi
exact_clustering/exact_clustering.abi3.so
exact_clustering/py.typed
exact_clustering-0.5.1.dist-info/RECORD
