Metadata-Version: 2.4
Name: exact-clustering
Version: 0.5.1
Classifier: Programming Language :: Rust
Classifier: Programming Language :: Python :: Implementation :: CPython
Classifier: Programming Language :: Python :: Implementation :: PyPy
License-File: LICENSE-APACHE
License-File: LICENSE-MIT
Summary: Find optimal clusterings and optimal hierarchical clusterings.
Keywords: clustering,k-means,k-median,optimization,algorithms
Author: lumi-a
License-Expression: MIT OR Apache-2.0
Requires-Python: >=3.10
Project-URL: Repository, https://github.com/lumi-a/py-exact-clustering
